allosaurus/__init__.py
allosaurus/app.py
allosaurus/audio.py
allosaurus/model.py
allosaurus/run.py
allosaurus/am/__init__.py
allosaurus/am/allosaurus_torch.py
allosaurus/am/criterion.py
allosaurus/am/dataset.py
allosaurus/am/factory.py
allosaurus/am/loader.py
allosaurus/am/optimizer.py
allosaurus/am/reporter.py
allosaurus/am/trainer.py
allosaurus/am/utils.py
allosaurus/bin/__init__.py
allosaurus/bin/adapt_model.py
allosaurus/bin/download_model.py
allosaurus/bin/list_lang.py
allosaurus/bin/list_model.py
allosaurus/bin/list_phone.py
allosaurus/bin/prep_feat.py
allosaurus/bin/prep_token.py
allosaurus/bin/remove_model.py
allosaurus/bin/restore_phone.py
allosaurus/bin/update_phone.py
allosaurus/bin/write_phone.py
allosaurus/lm/__init__.py
allosaurus/lm/articulatory.py
allosaurus/lm/decoder.py
allosaurus/lm/factory.py
allosaurus/lm/inventory.py
allosaurus/lm/mask.py
allosaurus/lm/unit.py
allosaurus/pm/__init__.py
allosaurus/pm/factory.py
allosaurus/pm/feature.py
allosaurus/pm/kdict.py
allosaurus/pm/mfcc.py
allosaurus/pm/preprocess.py
allosaurus/pm/utils.py
allosaurus-1.0.2.dist-info/LICENSE
allosaurus-1.0.2.dist-info/METADATA
allosaurus-1.0.2.dist-info/WHEEL
allosaurus-1.0.2.dist-info/top_level.txt
allosaurus-1.0.2.dist-info/RECORD
