Metadata-Version: 2.1
Name: allosaurus
Version: 1.0.2
Summary: a multilingual phone recognizer
Home-page: https://github.com/xinjli/allosaurus
Author: Xinjian Li
Author-email: xinjianl@cs.cmu.edu
License: UNKNOWN
Platform: UNKNOWN
License-File: LICENSE
Requires-Dist: scipy
Requires-Dist: numpy
Requires-Dist: resampy
Requires-Dist: panphon
Requires-Dist: torch
Requires-Dist: editdistance
